{"cameraMode":{"drawMode":0,"name":"Shaded","section":"Shading Mode"},"sceneLighting":true,"audioPlay":false,"sceneViewState":{"m_AlwaysRefresh":false,"showFog":true,"showSkybox":true,"showFlares":true,"showImageEffects":true,"showParticleSystems":true,"showVisualEffectGraphs":true,"m_FxEnabled":true},"in2DMode":false,"pivot":{"x":-9.239669799804688,"y":-4.214773178100586,"z":1.090388298034668},"rotation":{"x":-0.10548064857721329,"y":0.7206951379776001,"z":-0.1124691516160965,"w":-0.6758914589881897},"size":19.16476821899414,"orthographic":false}